{
  "groups": [
    {
      "title": "Default Content",
      "id": "default",
      "components": [
        {
          "title": "Text",
          "id": "text",
          "plugins": {
            "xwalk": {
              "page": {
                "resourceType": "core/franklin/components/text/v1/text",
                "template": {}
              }
            }
          }
        },
        {
          "title": "Title",
          "id": "title",
          "plugins": {
            "xwalk": {
              "page": {
                "resourceType": "core/franklin/components/title/v1/title",
                "template": {
                  "model": "title"
                }
              }
            }
          }
        },
        {
          "title": "Image",
          "id": "image",
          "plugins": {
            "xwalk": {
              "page": {
                "resourceType": "core/franklin/components/image/v1/image",
                "template": {}
              }
            }
          }
        },
        {
          "title": "Button",
          "id": "button",
          "plugins": {
            "xwalk": {
              "page": {
                "resourceType": "core/franklin/components/button/v1/button",
                "template": {
                  "model": "button"
                }
              }
            }
          }
        }
      ]
    },
    {
      "title": "Sections",
      "id": "sections",
      "components": [
        {
          "title": "AT&T Business Section",
          "id": "section-batt",
          "plugins": {
            "xwalk": {
              "page": {
                "resourceType": "core/franklin/components/section/v1/section",
                "template": {
                  "model": "section-batt",
                  "filter": "section-batt"
                }
              }
            }
          }
        }
      ]
    },
    {
      "title": "Blocks",
      "id": "blocks",
      "components": [
        {
          "title": "Accordion",
          "id": "accordion",
          "plugins": {
            "xwalk": {
              "page": {
                "resourceType": "core/franklin/components/block/v1/block",
                "template": {
                  "name": "Accordion",
                  "filter": "accordion"
                }
              }
            }
          }
        },
        {
          "title": "Accordion Item",
          "id": "accordion-item",
          "plugins": {
            "xwalk": {
              "page": {
                "resourceType": "core/franklin/components/block/v1/block/item",
                "template": {
                  "name": "Accordion Item",
                  "model": "accordion-item",
                  "summary": "Lorem Ipsum",
                  "text": "<p>Lorem ipsum dolor sit amet, consectetur adipiscing elit. Curabitur volutpat consequat dui, sit amet ...</p>"
                }
              }
            }
          }
        },
        {
          "title": "Batt Accordion",
          "id": "batt-accordion",
          "plugins": {
            "xwalk": {
              "page": {
                "resourceType": "core/franklin/components/block/v1/block",
                "template": {
                  "name": "Batt Accordion",
                  "filter": "batt-accordion"
                }
              }
            }
          }
        },
        {
          "title": "Accordion Item",
          "id": "batt-accordion-item",
          "plugins": {
            "xwalk": {
              "page": {
                "resourceType": "core/franklin/components/block/v1/block/item",
                "template": {
                  "name": "Accordion Item",
                  "model": "batt-accordion-item"
                }
              }
            }
          }
        },
        {
          "title": "Batt Anchor Tabs",
          "id": "batt-anchor-tabs",
          "plugins": {
            "xwalk": {
              "page": {
                "resourceType": "core/franklin/components/block/v1/block",
                "template": {
                  "name": "Batt Anchor Tabs",
                  "filter": "batt-anchor-tabs"
                }
              }
            }
          }
        },
        {
          "title": "Anchor Tab",
          "id": "batt-anchor-tab",
          "plugins": {
            "xwalk": {
              "page": {
                "resourceType": "core/franklin/components/block/v1/block/item",
                "template": {
                  "name": "Anchor Tab",
                  "model": "batt-anchor-tab"
                }
              }
            }
          }
        },
        {
          "title": "Batt Article",
          "id": "batt-article",
          "plugins": {
            "xwalk": {
              "page": {
                "resourceType": "core/franklin/components/block/v1/block",
                "template": {
                  "name": "Batt Article",
                  "model": "batt-article"
                }
              }
            }
          }
        },
        {
          "title": "Batt Banner",
          "id": "batt-banner",
          "plugins": {
            "xwalk": {
              "page": {
                "resourceType": "core/franklin/components/block/v1/block",
                "template": {
                  "name": "Batt Banner",
                  "model": "batt-banner"
                }
              }
            }
          }
        },
        {
          "title": "Batt Cards Feature",
          "id": "batt-cards-feature",
          "plugins": {
            "xwalk": {
              "page": {
                "resourceType": "core/franklin/components/block/v1/block",
                "template": {
                  "name": "Batt Cards Feature",
                  "filter": "batt-cards-feature"
                }
              }
            }
          }
        },
        {
          "title": "Feature Card",
          "id": "batt-feature-card",
          "plugins": {
            "xwalk": {
              "page": {
                "resourceType": "core/franklin/components/block/v1/block/item",
                "template": {
                  "name": "Feature Card",
                  "model": "batt-feature-card"
                }
              }
            }
          }
        },
        {
          "title": "Batt Cards Offer",
          "id": "batt-cards-offer",
          "plugins": {
            "xwalk": {
              "page": {
                "resourceType": "core/franklin/components/block/v1/block",
                "template": {
                  "name": "Batt Cards Offer",
                  "filter": "batt-cards-offer"
                }
              }
            }
          }
        },
        {
          "title": "Offer Card",
          "id": "batt-offer-card",
          "plugins": {
            "xwalk": {
              "page": {
                "resourceType": "core/franklin/components/block/v1/block/item",
                "template": {
                  "name": "Offer Card",
                  "model": "batt-offer-card"
                }
              }
            }
          }
        },
        {
          "title": "Batt Cards Product",
          "id": "batt-cards-product",
          "plugins": {
            "xwalk": {
              "page": {
                "resourceType": "core/franklin/components/block/v1/block",
                "template": {
                  "name": "Batt Cards Product",
                  "filter": "batt-cards-product"
                }
              }
            }
          }
        },
        {
          "title": "Product Card",
          "id": "batt-product-card",
          "plugins": {
            "xwalk": {
              "page": {
                "resourceType": "core/franklin/components/block/v1/block/item",
                "template": {
                  "name": "Product Card",
                  "model": "batt-product-card"
                }
              }
            }
          }
        },
        {
          "title": "Batt Cards Solution",
          "id": "batt-cards-solution",
          "plugins": {
            "xwalk": {
              "page": {
                "resourceType": "core/franklin/components/block/v1/block",
                "template": {
                  "name": "Batt Cards Solution",
                  "filter": "batt-cards-solution"
                }
              }
            }
          }
        },
        {
          "title": "Solution Card",
          "id": "batt-solution-card",
          "plugins": {
            "xwalk": {
              "page": {
                "resourceType": "core/franklin/components/block/v1/block/item",
                "template": {
                  "name": "Solution Card",
                  "model": "batt-solution-card"
                }
              }
            }
          }
        },
        {
          "title": "Batt Cards Story",
          "id": "batt-cards-story",
          "plugins": {
            "xwalk": {
              "page": {
                "resourceType": "core/franklin/components/block/v1/block",
                "template": {
                  "name": "Batt Cards Story",
                  "filter": "batt-cards-story"
                }
              }
            }
          }
        },
        {
          "title": "Story Card",
          "id": "batt-story-card",
          "plugins": {
            "xwalk": {
              "page": {
                "resourceType": "core/franklin/components/block/v1/block/item",
                "template": {
                  "name": "Story Card",
                  "model": "batt-story-card"
                }
              }
            }
          }
        },
        {
          "title": "Batt Columns",
          "id": "batt-columns",
          "plugins": {
            "xwalk": {
              "page": {
                "resourceType": "core/franklin/components/columns/v1/columns",
                "template": {
                  "name": "Batt Columns",
                  "model": "batt-columns",
                  "columns": 2,
                  "rows": 1
                }
              }
            }
          }
        },
        {
          "title": "Batt Comparison Table",
          "id": "batt-comparison-table",
          "plugins": {
            "xwalk": {
              "page": {
                "resourceType": "core/franklin/components/block/v1/block",
                "template": {
                  "name": "Batt Comparison Table",
                  "model": "batt-comparison-table"
                }
              }
            }
          }
        },
        {
          "title": "Batt Content Tabs",
          "id": "batt-content-tabs",
          "plugins": {
            "xwalk": {
              "page": {
                "resourceType": "core/franklin/components/block/v1/block",
                "template": {
                  "name": "Batt Content Tabs",
                  "filter": "batt-content-tabs"
                }
              }
            }
          }
        },
        {
          "title": "Tab Panel",
          "id": "batt-tab-panel",
          "plugins": {
            "xwalk": {
              "page": {
                "resourceType": "core/franklin/components/block/v1/block/item",
                "template": {
                  "name": "Tab Panel",
                  "model": "batt-tab-panel"
                }
              }
            }
          }
        },
        {
          "title": "Batt Form",
          "id": "batt-form",
          "plugins": {
            "xwalk": {
              "page": {
                "resourceType": "core/franklin/components/block/v1/block",
                "template": {
                  "name": "Batt Form",
                  "model": "batt-form"
                }
              }
            }
          }
        },
        {
          "title": "Batt Hero",
          "id": "batt-hero",
          "plugins": {
            "xwalk": {
              "page": {
                "resourceType": "core/franklin/components/block/v1/block",
                "template": {
                  "name": "Batt Hero",
                  "model": "batt-hero"
                }
              }
            }
          }
        },
        {
          "title": "Batt Pricing Cards",
          "id": "batt-pricing-cards",
          "plugins": {
            "xwalk": {
              "page": {
                "resourceType": "core/franklin/components/block/v1/block",
                "template": {
                  "name": "Batt Pricing Cards",
                  "filter": "batt-pricing-cards"
                }
              }
            }
          }
        },
        {
          "title": "Pricing Tier",
          "id": "batt-pricing-tier",
          "plugins": {
            "xwalk": {
              "page": {
                "resourceType": "core/franklin/components/block/v1/block/item",
                "template": {
                  "name": "Pricing Tier",
                  "model": "batt-pricing-tier"
                }
              }
            }
          }
        },
        {
          "title": "Batt SEO Links",
          "id": "batt-seo-links",
          "plugins": {
            "xwalk": {
              "page": {
                "resourceType": "core/franklin/components/block/v1/block",
                "template": {
                  "name": "Batt SEO Links",
                  "model": "batt-seo-links"
                }
              }
            }
          }
        },
        {
          "title": "Batt Service Grid",
          "id": "batt-service-grid",
          "plugins": {
            "xwalk": {
              "page": {
                "resourceType": "core/franklin/components/block/v1/block",
                "template": {
                  "name": "Batt Service Grid",
                  "filter": "batt-service-grid"
                }
              }
            }
          }
        },
        {
          "title": "Service Category",
          "id": "batt-service-category",
          "plugins": {
            "xwalk": {
              "page": {
                "resourceType": "core/franklin/components/block/v1/block/item",
                "template": {
                  "name": "Service Category",
                  "model": "batt-service-category"
                }
              }
            }
          }
        },
        {
          "title": "Batt Testimonial",
          "id": "batt-testimonial",
          "plugins": {
            "xwalk": {
              "page": {
                "resourceType": "core/franklin/components/block/v1/block",
                "template": {
                  "name": "Batt Testimonial",
                  "filter": "batt-testimonial"
                }
              }
            }
          }
        },
        {
          "title": "Testimonial Item",
          "id": "batt-testimonial-item",
          "plugins": {
            "xwalk": {
              "page": {
                "resourceType": "core/franklin/components/block/v1/block/item",
                "template": {
                  "name": "Testimonial Item",
                  "model": "batt-testimonial-item"
                }
              }
            }
          }
        },
        {
          "title": "Batt Value Prop",
          "id": "batt-value-prop",
          "plugins": {
            "xwalk": {
              "page": {
                "resourceType": "core/franklin/components/block/v1/block",
                "template": {
                  "name": "Batt Value Prop",
                  "model": "batt-value-prop"
                }
              }
            }
          }
        },
        {
          "title": "Cards",
          "id": "cards",
          "plugins": {
            "xwalk": {
              "page": {
                "resourceType": "core/franklin/components/block/v1/block",
                "template": {
                  "name": "Cards",
                  "filter": "cards"
                }
              }
            }
          }
        },
        {
          "title": "Card",
          "id": "card",
          "plugins": {
            "xwalk": {
              "page": {
                "resourceType": "core/franklin/components/block/v1/block/item",
                "template": {
                  "name": "Card",
                  "model": "card"
                }
              }
            }
          }
        },
        {
          "title": "Carousel",
          "id": "carousel",
          "plugins": {
            "xwalk": {
              "page": {
                "resourceType": "core/franklin/components/block/v1/block",
                "template": {
                  "name": "Carousel",
                  "filter": "carousel"
                }
              }
            }
          }
        },
        {
          "title": "Carousel Slide",
          "id": "carousel-item",
          "plugins": {
            "xwalk": {
              "page": {
                "resourceType": "core/franklin/components/block/v1/block/item",
                "template": {
                  "name": "Carousel Slide",
                  "model": "carousel-item"
                }
              }
            }
          }
        },
        {
          "title": "Columns",
          "id": "columns",
          "plugins": {
            "xwalk": {
              "page": {
                "resourceType": "core/franklin/components/columns/v1/columns",
                "template": {
                  "columns": "2",
                  "rows": "1"
                }
              }
            }
          }
        },
        {
          "title": "Embed",
          "id": "embed",
          "plugins": {
            "xwalk": {
              "page": {
                "resourceType": "core/franklin/components/block/v1/block",
                "template": {
                  "name": "Embed",
                  "model": "embed"
                }
              }
            }
          }
        },
        {
          "title": "Firstnet Cards News",
          "id": "firstnet-cards-news",
          "plugins": {
            "xwalk": {
              "page": {
                "resourceType": "core/franklin/components/block/v1/block",
                "template": {
                  "name": "Firstnet Cards News",
                  "filter": "firstnet-cards-news"
                }
              }
            }
          }
        },
        {
          "title": "News Card",
          "id": "news-card",
          "plugins": {
            "xwalk": {
              "page": {
                "resourceType": "core/franklin/components/block/v1/block/item",
                "template": {
                  "name": "News Card",
                  "model": "news-card"
                }
              }
            }
          }
        },
        {
          "title": "Firstnet Cards Offers",
          "id": "firstnet-cards-offers",
          "plugins": {
            "xwalk": {
              "page": {
                "resourceType": "core/franklin/components/block/v1/block",
                "template": {
                  "name": "Firstnet Cards Offers",
                  "filter": "firstnet-cards-offers"
                }
              }
            }
          }
        },
        {
          "title": "Offer Card",
          "id": "offer-card",
          "plugins": {
            "xwalk": {
              "page": {
                "resourceType": "core/franklin/components/block/v1/block/item",
                "template": {
                  "name": "Offer Card",
                  "model": "offer-card"
                }
              }
            }
          }
        },
        {
          "title": "Firstnet Columns",
          "id": "firstnet-columns",
          "plugins": {
            "xwalk": {
              "page": {
                "resourceType": "core/franklin/components/columns/v1/columns",
                "template": {
                  "columns": "3",
                  "rows": "1"
                }
              }
            }
          }
        },
        {
          "title": "Firstnet Form",
          "id": "firstnet-form",
          "plugins": {
            "xwalk": {
              "page": {
                "resourceType": "core/franklin/components/block/v1/block",
                "template": {
                  "name": "Firstnet Form",
                  "model": "firstnet-form"
                }
              }
            }
          }
        },
        {
          "title": "Firstnet Hero",
          "id": "firstnet-hero",
          "plugins": {
            "xwalk": {
              "page": {
                "resourceType": "core/franklin/components/block/v1/block",
                "template": {
                  "name": "Firstnet Hero",
                  "model": "firstnet-hero"
                }
              }
            }
          }
        },
        {
          "title": "Form",
          "id": "form",
          "plugins": {
            "xwalk": {
              "page": {
                "resourceType": "core/franklin/components/block/v1/block",
                "template": {
                  "name": "Form",
                  "model": "form"
                }
              }
            }
          }
        },
        {
          "title": "Fragment",
          "id": "fragment",
          "plugins": {
            "xwalk": {
              "page": {
                "resourceType": "core/franklin/components/block/v1/block",
                "template": {
                  "name": "Fragment",
                  "model": "fragment"
                }
              }
            }
          }
        },
        {
          "title": "Hero",
          "id": "hero",
          "plugins": {
            "xwalk": {
              "page": {
                "resourceType": "core/franklin/components/block/v1/block",
                "template": {
                  "name": "Hero",
                  "model": "hero"
                }
              }
            }
          }
        },
        {
          "title": "Modal",
          "id": "modal",
          "plugins": {
            "xwalk": {
              "page": {
                "resourceType": "core/franklin/components/block/v1/block",
                "template": {
                  "name": "Modal",
                  "model": "modal"
                }
              }
            }
          }
        },
        {
          "title": "Quote",
          "id": "quote",
          "plugins": {
            "xwalk": {
              "page": {
                "resourceType": "core/franklin/components/block/v1/block",
                "template": {
                  "name": "Quote",
                  "model": "quote"
                }
              }
            }
          }
        },
        {
          "title": "Search",
          "id": "search",
          "plugins": {
            "xwalk": {
              "page": {
                "resourceType": "core/franklin/components/block/v1/block",
                "template": {
                  "name": "Search",
                  "model": "search",
                  "filter": "search"
                }
              }
            }
          }
        },
        {
          "title": "Table",
          "id": "table",
          "plugins": {
            "xwalk": {
              "page": {
                "resourceType": "core/franklin/components/block/v1/block",
                "template": {
                  "name": "Table",
                  "model": "table",
                  "filter": "table"
                }
              }
            }
          }
        },
        {
          "title": "Row",
          "id": "table-row",
          "plugins": {
            "xwalk": {
              "page": {
                "resourceType": "core/franklin/components/block/v1/block/item",
                "template": {
                  "name": "Row",
                  "model": "table-row",
                  "column1text": "Column1"
                }
              }
            }
          }
        },
        {
          "title": "Row",
          "id": "table-col-2",
          "plugins": {
            "xwalk": {
              "page": {
                "resourceType": "core/franklin/components/block/v1/block/item",
                "template": {
                  "name": "Row",
                  "model": "table-col-2",
                  "column1text": "Column1",
                  "column2text": "Column2"
                }
              }
            }
          }
        },
        {
          "title": "Row",
          "id": "table-col-3",
          "plugins": {
            "xwalk": {
              "page": {
                "resourceType": "core/franklin/components/block/v1/block/item",
                "template": {
                  "name": "Row",
                  "model": "table-col-3",
                  "column1text": "Column1",
                  "column2text": "Column2",
                  "column3text": "Column3"
                }
              }
            }
          }
        },
        {
          "title": "Row",
          "id": "table-col-4",
          "plugins": {
            "xwalk": {
              "page": {
                "resourceType": "core/franklin/components/block/v1/block/item",
                "template": {
                  "name": "Row",
                  "model": "table-col-4",
                  "column1text": "Column1",
                  "column2text": "Column2",
                  "column3text": "Column3",
                  "column4text": "Column4"
                }
              }
            }
          }
        },
        {
          "title": "Tabs",
          "id": "tabs",
          "plugins": {
            "xwalk": {
              "page": {
                "resourceType": "core/franklin/components/block/v1/block",
                "template": {
                  "name": "Tabs",
                  "filter": "tabs"
                }
              }
            }
          }
        },
        {
          "title": "Tabs Item",
          "id": "tabs-item",
          "plugins": {
            "xwalk": {
              "page": {
                "resourceType": "core/franklin/components/block/v1/block/item",
                "template": {
                  "name": "Tab",
                  "model": "tabs-item",
                  "title": "Tab Name",
                  "content_headingType": "h3"
                }
              }
            }
          }
        },
        {
          "title": "Video",
          "id": "video",
          "plugins": {
            "xwalk": {
              "page": {
                "resourceType": "core/franklin/components/block/v1/block",
                "template": {
                  "name": "Video",
                  "model": "video",
                  "filter": "video"
                }
              }
            }
          }
        }
      ]
    }
  ]
}